ava_mosaic_ai/__init__.py
ava_mosaic_ai/config/settings.py
ava_mosaic_ai/llm_factory.py
ava_mosaic_ai/utils/utils.py
ava_mosaic_ai-0.1.9.dist-info/LICENSE
ava_mosaic_ai-0.1.9.dist-info/METADATA
ava_mosaic_ai-0.1.9.dist-info/WHEEL
ava_mosaic_ai-0.1.9.dist-info/RECORD
