Metadata-Version: 2.1
Name: ava-mosaic-ai
Version: 0.1.9
Summary: 
Home-page: https://github.com/pyrotank41/Mosaic-AI.git
Author: Karan Singh Kochar
Author-email: pyrotank41@gmail.com
Requires-Python: >=3.11,<4.0
Classifier: Programming Language :: Python :: 3
Classifier: Programming Language :: Python :: 3.11
Classifier: Programming Language :: Python :: 3.12
Classifier: Programming Language :: Python :: 3.13
Requires-Dist: anthropic (>=0.34.0,<0.35.0)
Requires-Dist: instructor (>=1.3.7,<2.0.0)
Requires-Dist: openai (>=1.41.0,<2.0.0)
Requires-Dist: portkey-ai (>=1.8.7,<2.0.0)
Requires-Dist: pydantic (>=2.7.0,<3)
Requires-Dist: pytest (>=8.3.2,<9.0.0)
Requires-Dist: python-dotenv (>=1.0.1,<2.0.0)
Requires-Dist: tiktoken (>=0.7.0,<0.8.0)
Project-URL: Repository, https://github.com/pyrotank41/Mosaic-AI.git
